pybfx/__init__.py
pybfx/__main__.py
pybfx/cli.py
pybfx/rest/__init__.py
pybfx/rest/client.py
pybfx-0.2.0.dist-info/METADATA
pybfx-0.2.0.dist-info/RECORD
pybfx-0.2.0.dist-info/WHEEL
pybfx-0.2.0.dist-info/entry_points.txt
pybfx-0.2.0.dist-info/top_level.txt
